gui_util/__init__.py
gui_util/cli.py
gui_util/gui.py
gui_util/window.py
gui_util-0.1.4.dist-info/entry_points.txt
gui_util-0.1.4.dist-info/WHEEL
gui_util-0.1.4.dist-info/METADATA
gui_util-0.1.4.dist-info/RECORD
